Metadata-Version: 2.1
Name: aiotoolz
Version: 0.0.2
Summary: List processing tools and functional utilities (Ported to support async/await)
Home-page: https://github.com/eabrouwer3/aiotoolz/
Author: https://raw.github.com/eabrouwer3/aiotoolz/master/AUTHORS.md
Maintainer: Ethan Brouwer
Maintainer-email: eabrouwer3@gmail.com
License: BSD
Keywords: functional utility itertools functools
Platform: UNKNOWN
Classifier: Development Status :: 2 - Pre-Alpha
Classifier: License :: OSI Approved :: BSD License
Classifier: Programming Language :: Python
Classifier: Programming Language :: Python :: 3.5
Classifier: Programming Language :: Python :: 3.6
Classifier: Programming Language :: Python :: 3.7
Requires-Python: >=3.5
